requisite_processor/__init__.py
requisite_processor/requisite_check.py
requisite_processor/requisite_processor.py
requisite_processor-0.2.6.dist-info/METADATA
requisite_processor-0.2.6.dist-info/WHEEL
requisite_processor-0.2.6.dist-info/RECORD
