Metadata-Version: 2.3
Name: requisite_processor
Version: 0.2.6
Summary: Module for working with course requisite data and checking requisite satisfaciton.
Author: Michael Hickman
Author-email: mhickman@unm.edu
Requires-Python: >=3.10,<4.0
Classifier: Programming Language :: Python :: 3
Classifier: Programming Language :: Python :: 3.10
Classifier: Programming Language :: Python :: 3.11
Classifier: Programming Language :: Python :: 3.12
Classifier: Programming Language :: Python :: 3.13
